felicien/__init__.py
felicien/feliconnector.py
felicien/felits.py
felicien-0.8.1.dist-info/LICENSE
felicien-0.8.1.dist-info/METADATA
felicien-0.8.1.dist-info/WHEEL
felicien-0.8.1.dist-info/RECORD
