Metadata-Version: 2.1
Name: felicien
Version: 0.8.1
Summary: Felicien is you companion to retrieve timeseries from a TSDB, to transform it in various format and to push it to a TSDB.
License: MIT
Author: Julien Andrieux
Author-email: chilladx@pm.me
Requires-Python: >=3.11,<4.0
Classifier: License :: OSI Approved :: MIT License
Classifier: Programming Language :: Python :: 3
Classifier: Programming Language :: Python :: 3.11
Requires-Dist: matplotlib (>=3.8.4,<4.0.0)
Requires-Dist: pandas (>=2.2.1,<3.0.0)
Requires-Dist: pandas-stubs (>=2.2.1.240316,<3.0.0.0)
Requires-Dist: requests (>=2.31.0,<3.0.0)
Requires-Dist: requests-mock (>=1.12.1,<2.0.0)
Requires-Dist: types-requests (>=2.31.0.20240406,<3.0.0.0)
Requires-Dist: validators (>=0.27.0,<0.28.0)
